casestyle
