Metadata-Version: 1.2
Name: casestyle
Version: 0.0.2
Summary: String case style converter (snake_case, camelCase, PascalCase, dash-case, CONST_CASE can be converted to each other).
Home-page: https://github.com/zhoujin7/casestyle
Author: zhoujin7
Author-email: zhoujin7@foxmail.com
License: Apache License 2.0
Keywords: casestyle,inflection,stringcase,humps,snake case,camel case,pascal case,dash case,const case
Platform: UNKNOWN
Classifier: Development Status :: 4 - Beta
Classifier: Intended Audience :: Developers
Classifier: Natural Language :: English
Classifier: License :: OSI Approved :: Apache Software License
Classifier: Programming Language :: Python
Classifier: Programming Language :: Python :: 3
Classifier: Programming Language :: Python :: 3.4
Classifier: Programming Language :: Python :: 3.5
Classifier: Programming Language :: Python :: 3.6
Classifier: Programming Language :: Python :: 3.7
Classifier: Programming Language :: Python :: 3.8
Classifier: Programming Language :: Python :: Implementation :: CPython
Classifier: Programming Language :: Python :: Implementation :: PyPy
Requires-Python: >=3
